mcp_weather_streamable/__init__.py
mcp_weather_streamable/__main__.py
mcp_weather_streamable/server.py
mcp_weather_streamable-0.1.0.dist-info/METADATA
mcp_weather_streamable-0.1.0.dist-info/WHEEL
mcp_weather_streamable-0.1.0.dist-info/entry_points.txt
mcp_weather_streamable-0.1.0.dist-info/top_level.txt
mcp_weather_streamable-0.1.0.dist-info/RECORD
