Metadata-Version: 2.4
Name: mcp-weather-streamable
Version: 0.1.0
Summary: 输入OpenWeather-API-KEY，获取天气信息。
Requires-Python: >=3.11
Requires-Dist: httpx>=0.28.1
Requires-Dist: mcp>=1.9.1
